pypi_download_stats/__init__.py
pypi_download_stats/dataquery.py
pypi_download_stats/diskdatacache.py
pypi_download_stats/graphs.py
pypi_download_stats/outputgenerator.py
pypi_download_stats/projectstats.py
pypi_download_stats/runner.py
pypi_download_stats/version.py
pypi_download_stats/templates/badges.html
pypi_download_stats/templates/base.html
pypi_download_stats/templates/graph_macro.html
pypi_download_stats/templates/nav.html
pypi_download_stats/tests/__init__.py
pypi_download_stats/tests/test_runner.py
pypi_download_stats/tests/test_version.py
pypi_download_stats-0.2.1.dist-info/DESCRIPTION.rst
pypi_download_stats-0.2.1.dist-info/METADATA
pypi_download_stats-0.2.1.dist-info/RECORD
pypi_download_stats-0.2.1.dist-info/WHEEL
pypi_download_stats-0.2.1.dist-info/entry_points.txt
pypi_download_stats-0.2.1.dist-info/metadata.json
pypi_download_stats-0.2.1.dist-info/top_level.txt
