Metadata-Version: 2.0
Name: pypi-download-stats
Version: 0.2.1
Summary: Calculate detailed download stats and generate HTML and badges for PyPI packages
Home-page: https://github.com/jantman/pypi-download-stats
Author: Jason Antman
Author-email: jason@jasonantman.com
License: UNKNOWN
Keywords: pypi warehouse download stats badge
Platform: UNKNOWN
Classifier: Development Status :: 3 - Alpha
Classifier: Environment :: Console
Classifier: Intended Audience :: Developers
Classifier: License :: OSI Approved :: GNU Affero General Public License v3 or later (AGPLv3+)
Classifier: Natural Language :: English
Classifier: Operating System :: OS Independent
Classifier: Programming Language :: Python
Classifier: Programming Language :: Python :: 2.7
Classifier: Programming Language :: Python :: 3
Classifier: Topic :: Internet :: Log Analysis
Classifier: Topic :: Software Development
Classifier: Topic :: Utilities
Requires-Dist: bokeh (==0.12.1)
Requires-Dist: google-api-python-client (>=1.5.0)
Requires-Dist: iso3166
Requires-Dist: oauth2client (>=3.0.0)
Requires-Dist: pandas (<1.0,>=0.18)
Requires-Dist: pytz
Requires-Dist: requests (<3.0,>2.0)
Requires-Dist: tzlocal
